soliloquy/__init__.py
soliloquy/cli.py
soliloquy/ops/__init__.py
soliloquy/ops/analyze_ops.py
soliloquy/ops/build_ops.py
soliloquy/ops/format_ops.py
soliloquy/ops/git_ops.py
soliloquy/ops/install_ops.py
soliloquy/ops/lint_ops.py
soliloquy/ops/lock_ops.py
soliloquy/ops/poetry_utils.py
soliloquy/ops/publish_ops.py
soliloquy/ops/pyproject_ops.py
soliloquy/ops/remote_ops.py
soliloquy/ops/test_ops.py
soliloquy/ops/version_ops.py
soliloquy/phases/__init__.py
soliloquy/phases/install.py
soliloquy/phases/prepare.py
soliloquy/phases/release.py
soliloquy/phases/validate.py
soliloquy-0.1.2.dist-info/LICENSE
soliloquy-0.1.2.dist-info/METADATA
soliloquy-0.1.2.dist-info/WHEEL
soliloquy-0.1.2.dist-info/entry_points.txt
soliloquy-0.1.2.dist-info/RECORD
